layrageu/__init__.py
layrageu/__main__.py
layrageu/fodt2text.py
layrageu/gui.py
layrageu/loader.py
layrageu/sender.py
layrageu/settings.py
layrageu/tui.py
layrageu-0.2.1.dist-info/LICENSE
layrageu-0.2.1.dist-info/METADATA
layrageu-0.2.1.dist-info/WHEEL
layrageu-0.2.1.dist-info/entry_points.txt
layrageu-0.2.1.dist-info/top_level.txt
layrageu-0.2.1.dist-info/RECORD
